dcnotifier/DCNotifier.py
dcnotifier/__init__.py
dcnotifier-0.1.0.dist-info/licenses/LICENSE
dcnotifier-0.1.0.dist-info/METADATA
dcnotifier-0.1.0.dist-info/WHEEL
dcnotifier-0.1.0.dist-info/top_level.txt
dcnotifier-0.1.0.dist-info/RECORD
