Metadata-Version: 2.4
Name: dcnotifier
Version: 0.1.0
Summary: Biblioteca para enviar notificações para o Discord de forma simples e rápida. Uso principal em aplicações de monitoramento.
Home-page: https://github.com/Maraba23/DCNotifier
Author: Marcelo Rabello Barranco
Author-email: rabello.barranco@gmail.com
License: Apache-2.0
Keywords: discord,notifications,webhook
Classifier: Programming Language :: Python :: 3
Classifier: License :: OSI Approved :: Apache Software License
Classifier: Operating System :: OS Independent
Requires-Python: >=3.11
License-File: LICENSE
Requires-Dist: requests
Dynamic: author
Dynamic: author-email
Dynamic: classifier
Dynamic: description
Dynamic: description-content-type
Dynamic: home-page
Dynamic: keywords
Dynamic: license
Dynamic: license-file
Dynamic: requires-dist
Dynamic: requires-python
Dynamic: summary
